hellopy/__init__.py
hellopy/hello.py
hellopy/data/data.dat
hellopy/data/demo.ico
hellopy/opts/__init__.py
hellopy/opts/const.py
hellopy/utils/__init__.py
hellopy/utils/tool.py
Cynthia-1.0.5.dist-info/LICENSE.txt
Cynthia-1.0.5.dist-info/METADATA
Cynthia-1.0.5.dist-info/WHEEL
Cynthia-1.0.5.dist-info/entry_points.txt
Cynthia-1.0.5.dist-info/top_level.txt
Cynthia-1.0.5.dist-info/RECORD
