Metadata-Version: 2.1
Name: Cynthia
Version: 1.0.5
Summary: A sample Python project
Home-page: https://github.com/pypa/sampleproject
Author: Cynthia
Author-email: bbliu666@126.com
License: UNKNOWN
Project-URL: Bug Reports, https://github.com/pypa/sampleproject
Project-URL: Funding, https://github.com/pypa/sampleproject
Project-URL: Say Thanks!, https://github.com/pypa/sampleproject
Project-URL: Source, https://github.com/pypa/sampleproject
Keywords: sample setuptools development
Platform: UNKNOWN
Classifier: Development Status :: 3 - Alpha
Classifier: Intended Audience :: Developers
Classifier: Topic :: Software Development :: Build Tools
Classifier: License :: OSI Approved :: MIT License
Classifier: Programming Language :: Python :: 3.5
Classifier: Programming Language :: Python :: 3.6
Classifier: Programming Language :: Python :: 3.7
Classifier: Programming Language :: Python :: 3.8
Requires-Python: >=3.5, !=3.0.*, <4
Requires-Dist: setuptools (>=41.1.0)
Requires-Dist: wheel
Provides-Extra: dev
Requires-Dist: twine ; extra == 'dev'
Provides-Extra: test
Requires-Dist: twine ; extra == 'test'
